climatic_python/Python3Shell.py
climatic_python/__init__.py
climatic_python-0.0.2.dist-info/LICENSE
climatic_python-0.0.2.dist-info/METADATA
climatic_python-0.0.2.dist-info/WHEEL
climatic_python-0.0.2.dist-info/top_level.txt
climatic_python-0.0.2.dist-info/RECORD
